Rcolor/__init__.py
Rcolor/rcolor.py
Rcolor/colors/__init__.py
Rcolor/colors/background_colors.json
Rcolor/colors/foreground.json
Rcolor/colors/standard_background.json
Rcolor/colors/standard_colors.json
Rcolor/colors/style1.json
Rcolor-3.0.1.dist-info/LICENSE
Rcolor-3.0.1.dist-info/METADATA
Rcolor-3.0.1.dist-info/WHEEL
Rcolor-3.0.1.dist-info/top_level.txt
Rcolor-3.0.1.dist-info/RECORD
