Metadata-Version: 2.1
Name: Rcolor
Version: 3.0.1
Summary: A library that makes your output colorful in Python
Home-page: https://github.com/ibehii/RandomColorlib
Author: Behnam
Author-email: Behii@tutanota.com
License: MIT
Keywords: Randomly change your output color
Classifier: Programming Language :: Python :: 3
Classifier: Operating System :: OS Independent
Requires-Python: ~=3.6
License-File: LICENSE
Requires-Dist: colorama
